notification_mcp_server/__init__.py
notification_mcp_server/__main__.py
notification_mcp_server/server.py
notification_mcp_server/tools/__init__.py
notification_mcp_server/tools/registry.py
notification_mcp_server/utils/__init__.py
notification_mcp_server/utils/pushover_client.py
notification_mcp_server/utils/sendgrid_client.py
notification_mcp_server-0.1.0.dist-info/METADATA
notification_mcp_server-0.1.0.dist-info/WHEEL
notification_mcp_server-0.1.0.dist-info/entry_points.txt
notification_mcp_server-0.1.0.dist-info/RECORD
