Metadata-Version: 2.4
Name: notification-mcp-server
Version: 0.1.0
Summary: MCP server for sending notifications via SendGrid email and Pushover push notifications
Author-email: Your Name <you@example.com>
License: MIT
Keywords: email,llm,mcp,notification,push,pushover,sendgrid
Classifier: Development Status :: 4 - Beta
Classifier: Intended Audience :: Developers
Classifier: License :: OSI Approved :: MIT License
Classifier: Programming Language :: Python :: 3.12
Requires-Python: >=3.12
Requires-Dist: httpx>=0.25.0
Requires-Dist: mcp>=1.24.0
Requires-Dist: pydantic>=2.0.0
Provides-Extra: dev
Requires-Dist: pytest-asyncio>=0.24.0; extra == 'dev'
Requires-Dist: pytest>=8.0.0; extra == 'dev'
Requires-Dist: respx>=0.21.0; extra == 'dev'
Requires-Dist: ruff>=0.8.0; extra == 'dev'
